phpserialize.py
setup.py
phpserialize.egg-info/PKG-INFO
phpserialize.egg-info/SOURCES.txt
phpserialize.egg-info/dependency_links.txt
phpserialize.egg-info/top_level.txt