Metadata-Version: 1.0
Name: phpserialize
Version: 1.1
Summary: a port of the serialize and unserialize functions of php to python.
Home-page: http://dev.pocoo.org/hg/phpserialize-main
Author: Armin Ronacher
Author-email: armin.ronacher@active-4.com
License: UNKNOWN
Platform: UNKNOWN
Classifier: License :: OSI Approved :: BSD License
Classifier: Programming Language :: PHP
Classifier: Programming Language :: Python
